kafka_scanner/__init__.py
kafka_scanner/exceptions.py
kafka_scanner/msg_processor.py
kafka_scanner/msg_processor_handlers.py
kafka_scanner/tests/__init__.py
kafka_scanner-0.3.2.dist-info/DESCRIPTION.rst
kafka_scanner-0.3.2.dist-info/METADATA
kafka_scanner-0.3.2.dist-info/RECORD
kafka_scanner-0.3.2.dist-info/WHEEL
kafka_scanner-0.3.2.dist-info/metadata.json
kafka_scanner-0.3.2.dist-info/top_level.txt
