Metadata-Version: 1.1
Name: kafka-scanner
Version: 0.3.2
Summary: High Level Kafka Scanner, supporting inverse consuming and deduplication. Based on kafka-python library.
Home-page: https://github.com/scrapinghub/kafka-scanner
Author: Scrapinghub
Author-email: info@scrapinghub.com
License: BSD
Keywords: kafka
Platform: UNKNOWN
Classifier: Development Status :: 4 - Beta
Classifier: Intended Audience :: Developers
Classifier: License :: OSI Approved :: BSD License
Classifier: Operating System :: OS Independent
Classifier: Programming Language :: Python
Classifier: Programming Language :: Python :: 2.7
Classifier: Programming Language :: Python :: 3
